CHANGELOG.md
MANIFEST.in
README.md
_upload.txt
requirements.txt
setup.py
_deprecated/__init__BACKUP.py
_deprecated/__init__BACKUP_LVL2.py
_deprecated/record_v4.5.1.py
_manifesto/Manifesto.md
_testassets/D_autoinit.py
_testassets/D_colordict.py
_testassets/D_inputdict.py
_testassets/T_MC.py
_testassets/T_complexTypes.py
_testassets/T_customColoring.py
_testassets/T_dynamicScript.py
_testassets/T_dynamicWheel.py
_testassets/T_staticScript.py
_testassets/T_staticWheel.py
duality/__init__.py
duality.egg-info/PKG-INFO
duality.egg-info/SOURCES.txt
duality.egg-info/dependency_links.txt
duality.egg-info/requires.txt
duality.egg-info/top_level.txt
duality/decorators/__init__.py
duality/decorators/dualityapp.py
duality/decorators/dualitytrack.py
duality/misc/__init__.py
duality/misc/_meta.py