Metadata-Version: 2.1
Name: duality
Version: 5.4.5
Summary: Decorator library for the creation of CLI applications and scripts.
Home-page: http://github.com/dkundih/duality
Author: David Kundih
Author-email: kundihdavid@gmail.com
Maintainer: David Kundih
Maintainer-email: kundihdavid@gmail.com
License: Apache Software License
Download-URL: https://github.com/dkundih/duality/archive/refs/tags/v5.4.5.tar.gz
Project-URL: Documentation, https://github.com/dkundih/duality/blob/master/README.md
Project-URL: Source Code, https://github.com/dkundih/duality/tree/master/duality
Keywords: script,CLI,data manipulation,decorator,decorator functions,unin,duality,duality-py,duality.py,vandal,vandal.py,vandal-py
Platform: UNKNOWN
Classifier: Development Status :: 5 - Production/Stable
Classifier: Intended Audience :: Education
Classifier: Intended Audience :: Science/Research
Classifier: Intended Audience :: Customer Service
Classifier: Intended Audience :: Financial and Insurance Industry
Classifier: Operating System :: Microsoft :: Windows :: Windows 7
Classifier: Operating System :: Microsoft :: Windows :: Windows 8
Classifier: Operating System :: Microsoft :: Windows :: Windows 8.1
Classifier: Operating System :: Microsoft :: Windows :: Windows 10
Classifier: License :: OSI Approved :: Apache Software License
Classifier: Programming Language :: Python
Classifier: Programming Language :: Python :: 3 :: Only
Classifier: Programming Language :: Python :: 3.5
Classifier: Programming Language :: Python :: 3.6
Classifier: Programming Language :: Python :: 3.7
Classifier: Programming Language :: Python :: 3.8
Classifier: Programming Language :: Python :: 3.9
Classifier: Programming Language :: Python :: 3.10
Classifier: Topic :: Database
Classifier: Topic :: Education
Classifier: Topic :: Scientific/Engineering :: Artificial Intelligence
Classifier: Topic :: Scientific/Engineering :: Visualization
Classifier: Topic :: Office/Business :: Financial :: Investment
Classifier: Topic :: Office/Business :: Financial :: Accounting
Classifier: Topic :: Office/Business :: Financial :: Point-Of-Sale
Classifier: Topic :: Office/Business :: Financial :: Spreadsheet
